[
{
        "FirstName": "adam",
        "LastName": "taoussi",
        "DateOfBirth": "2007-01-11",
        "PlaceOfBirth": "rabat hassan",
        "Gender": "male",
        "PassportNo": "UQ7946071",
        "IssueDate": "2025-04-15",
        "IssuePlace": "FQUIH BEN SALAH",
        "ExpiryDate": "2030-04-15",
        "Email": "yassine.elouassile@gmail.com",
        "visatype": "STUDENT ",
        "PhotoId": "62fe7a45-c614-43a7-aedc-cbdd1edaf231"

    },

  {
        "FirstName": "AHMED",
        "LastName": "CHARKAOUI",
        "DateOfBirth": "1953-01-01",
        "PlaceOfBirth": "BNI KHLOUG",
        "Gender": "Male",
        "PassportNo": "LR5823413",
        "IssueDate": "2021-12-29",
        "IssuePlace": "SETTAT",
        "ExpiryDate": "2026-12-29",
        "Email": "yassine.elouassile@gmail.com",
        "visatype": "National",
        "PhotoId": "fe839ca0-a038-4f6d-b114-224e8112a7dc"

    },
 {
        "FirstName": "OTHMAN",
        "LastName": "ECH CHAOUI",
        "DateOfBirth": "2003-08-13",
        "PlaceOfBirth": "sidi MOUSSA",
        "Gender": "Male",
        "PassportNo": "WA5939198",
        "IssueDate": "2022-08-12",
        "IssuePlace": "EL KELAA DES SRAGHNA",
        "ExpiryDate": "2027-08-12",
        "Email": "yassine.elouassile@gmail.com",
        "visatype": "SPAIN WORK",
        "PhotoId": "1513e7d8-9b61-486a-a707-175d024e9e63"
    },
    {
        "FirstName": "KAMAL",
        "LastName": "KENSAOUI",
        "DateOfBirth": "1978-12-16",
        "PlaceOfBirth": "AIN SBAI",
        "Gender": "Male",
        "PassportNo": "YA0246514",
        "IssueDate": "2025-05-29",
        "IssuePlace": "CASABLANCA",
        "ExpiryDate": "2030-05-29",
        "Email": "yassine.elouassile@gmail.com",
        "visatype": "PORTUGAL",
        "PhotoId": "fe839ca0-a038-4f6d-b114-224e8112a7dc"
    },
    {
        "FirstName": "ADAM",
        "LastName": "TAOUSSI",
        "DateOfBirth": "2007-01-11",
        "PlaceOfBirth": "RABAT HASSAN",
        "Gender": "male",
        "PassportNo": "UQ7946071",
        "IssueDate": "2025-04-15",
        "IssuePlace": "FQUIH BEN SALAH",
        "ExpiryDate": "2030-04-15",
        "Email": "yassine.elouassile@gmail.com",
        "visatype": "SPAIN WORK",
        "PhotoId": "fe839ca0-a038-4f6d-b114-224e8112a7dc"
    },
    {
        "FirstName": "AHMED",
        "LastName": "SOUBHI",
        "DateOfBirth": "1955-01-01",
        "PlaceOfBirth": "OULEAD HASSOUNE",
        "Gender": "female",
        "PassportNo": "KT0758980",
        "IssueDate": "2024-10-24",
        "IssuePlace": "SETTAT",
        "ExpiryDate": "2029-10-24",
        "Email": "yassine.elouassile@gmail.com",
        "visatype": "SPAIN CASA1",
        "PhotoId": "fe839ca0-a038-4f6d-b114-224e8112a7dc"
    },
    {
        "FirstName": "ZAKARIA",
        "LastName": "SERRAR",
        "DateOfBirth": "2002-02-24",
        "PlaceOfBirth": "EL BOROUJ",
        "Gender": "Male",
        "PassportNo": "LX5496100",
        "IssueDate": "2021-10-25",
        "IssuePlace": "SETTAT",
        "ExpiryDate": "2026-10-25",
        "Email": "yassine.elouassile@gmail.com",
        "visatype": "SPAIN CASA1",
        "PhotoId": "fe839ca0-a038-4f6d-b114-224e8112a7dc"
    },
    
   
    {
        "FirstName": "AZZADINE",
        "LastName": "JBILAT",
        "DateOfBirth": "1985-01-26",
        "PlaceOfBirth": "AIN SBAA",
        "Gender": "Male",
        "PassportNo": "ET9372741",
        "IssueDate": "2023-08-11",
        "IssuePlace": "CASABLANCA",
        "ExpiryDate": "2028-08-11",
        "Email": "yassine.elouassile@gmail.com",
        "visatype": "PORTUGAL TOURISME",
        "PhotoId": "fe839ca0-a038-4f6d-b114-224e8112a7dc"
    }
]
